bigflow/__init__.py
bigflow/__main__.py
bigflow/_version.py
bigflow/cli.py
bigflow/commons.py
bigflow/configuration.py
bigflow/dagbuilder.py
bigflow/deploy.py
bigflow/konfig.py
bigflow/migrate.py
bigflow/resources.py
bigflow/version.py
bigflow/workflow.py
bigflow/bigquery/__init__.py
bigflow/bigquery/dataset_configuration.py
bigflow/bigquery/dataset_manager.py
bigflow/bigquery/interactive.py
bigflow/bigquery/interface.py
bigflow/bigquery/job.py
bigflow/build/__init__.py
bigflow/build/dev.py
bigflow/build/dist.py
bigflow/build/legacy.py
bigflow/build/meta.py
bigflow/build/operate.py
bigflow/build/pip.py
bigflow/build/reflect.py
bigflow/build/spec.py
bigflow/build/dataflow/__init__.py
bigflow/dataflow/__init__.py
bigflow/dataflow/io.py
bigflow/dataflow/job.py
bigflow/dataflow/ml.py
bigflow/dataflow/options.py
bigflow/scaffold/__init__.py
bigflow/scaffold/infra.py
bigflow/scaffold/scaffold.py
bigflow/scaffold/templating.py
bigflow/scaffold/templates/README.txt
bigflow/scaffold/templates/migrate-11/pyproject.toml.j2
bigflow/scaffold/templates/new-project/.gitignore.j2
bigflow/scaffold/templates/new-project/Dockerfile
bigflow/scaffold/templates/new-project/README.md
bigflow/scaffold/templates/new-project/deployment_config.py.j2
bigflow/scaffold/templates/new-project/pyproject.toml.j2
bigflow/scaffold/templates/new-project/setup.py.j2
bigflow/scaffold/templates/new-project/resources/requirements.in.j2
bigflow/scaffold/templates/new-project/test/__init__.py.j2
bigflow/scaffold/templates/new-project/test/test_wordcount_workflow.py.j2
bigflow/scaffold/templates/new-project/test/pi_estimator/__init__.py.j2
bigflow/scaffold/templates/new-project/test/pi_estimator/test_processing.py.j2
bigflow/scaffold/templates/new-project/{{project_name}}/__init__.py.j2
bigflow/scaffold/templates/new-project/{{project_name}}/internationalports/__init__.py.j2
bigflow/scaffold/templates/new-project/{{project_name}}/internationalports/workflow.py.j2
bigflow-1.11.3.dist-info/licenses/LICENSE
bigflow-1.11.3.dist-info/licenses/NOTICE
bigflow-1.11.3.dist-info/METADATA
bigflow-1.11.3.dist-info/WHEEL
bigflow-1.11.3.dist-info/top_level.txt
bigflow-1.11.3.dist-info/RECORD
