Metadata-Version: 2.4
Name: bigflow
Version: 1.11.3
Summary: BigQuery client wrapper with clean API
Home-page: https://github.com/allegro/bigflow
Author: Pogranicze
Author-email: pogranicze-team@allegro.pl
Classifier: Programming Language :: Python :: 3.8
Classifier: Programming Language :: Python :: 3.9
Classifier: Programming Language :: Python :: 3.10
Classifier: Operating System :: OS Independent
License-File: LICENSE
License-File: NOTICE
Requires-Dist: grpcio-status<=1.48.2
Requires-Dist: google-cloud-storage<3,>=2
Requires-Dist: MarkupSafe>2.1.0
Requires-Dist: google-auth<3,>=1.20
Requires-Dist: unittest-xml-reporting<4,>=3.0.2
Requires-Dist: jinja2<4,>=3
Requires-Dist: pip-tools<8,>=7
Requires-Dist: deprecated<2,>=1.2.10
Requires-Dist: toml>=0.10
Requires-Dist: tblib<2,>=1.7
Requires-Dist: numpy<2
Requires-Dist: typing-extensions>=3.7
Requires-Dist: backports.cached-property; python_version <= "3.8"
Requires-Dist: lazy-object-proxy<2,>=1
Requires-Dist: wheel<=0.45.1,>=0.35
Requires-Dist: setuptools>=45
Provides-Extra: bigquery
Requires-Dist: google-cloud-bigquery<4,>=1.6; extra == "bigquery"
Requires-Dist: db-dtypes>=1.0.5; extra == "bigquery"
Requires-Dist: pandas<2,>=0.25; extra == "bigquery"
Requires-Dist: six<2,>=1.14; extra == "bigquery"
Provides-Extra: dataflow
Requires-Dist: apache-beam[gcp]==2.60; extra == "dataflow"
Provides-Extra: base-frozen
Requires-Dist: backports-cached-property==1.0.1; python_version <= "3.8" and extra == "base-frozen"
Requires-Dist: cachetools==5.0.0; extra == "base-frozen"
Requires-Dist: certifi==2021.10.8; extra == "base-frozen"
Requires-Dist: charset-normalizer==2.0.12; extra == "base-frozen"
Requires-Dist: click==8.0.4; extra == "base-frozen"
Requires-Dist: deprecated==1.2.13; extra == "base-frozen"
Requires-Dist: google-api-core==2.7.1; extra == "base-frozen"
Requires-Dist: google-auth==2.6.2; extra == "base-frozen"
Requires-Dist: google-cloud-core==2.3.2; extra == "base-frozen"
Requires-Dist: google-cloud-storage==2.9.0; extra == "base-frozen"
Requires-Dist: google-crc32c==1.3.0; extra == "base-frozen"
Requires-Dist: google-resumable-media==2.3.2; extra == "base-frozen"
Requires-Dist: googleapis-common-protos==1.56.0; extra == "base-frozen"
Requires-Dist: grpcio==1.50.0; extra == "base-frozen"
Requires-Dist: grpcio-status==1.48.2; extra == "base-frozen"
Requires-Dist: idna==3.3; extra == "base-frozen"
Requires-Dist: jinja2==3.1.2; extra == "base-frozen"
Requires-Dist: lazy-object-proxy==1.7.1; extra == "base-frozen"
Requires-Dist: lxml==4.8.0; extra == "base-frozen"
Requires-Dist: markupsafe==2.1.1; extra == "base-frozen"
Requires-Dist: pep517==0.12.0; extra == "base-frozen"
Requires-Dist: pip-tools==6.5.1; extra == "base-frozen"
Requires-Dist: protobuf==3.19.4; extra == "base-frozen"
Requires-Dist: pyasn1==0.4.8; extra == "base-frozen"
Requires-Dist: pyasn1-modules==0.2.8; extra == "base-frozen"
Requires-Dist: requests==2.27.1; extra == "base-frozen"
Requires-Dist: rsa==4.8; extra == "base-frozen"
Requires-Dist: six==1.16.0; extra == "base-frozen"
Requires-Dist: tblib==1.7.0; extra == "base-frozen"
Requires-Dist: toml==0.10.2; extra == "base-frozen"
Requires-Dist: tomli==2.0.1; extra == "base-frozen"
Requires-Dist: typing-extensions==3.10.0.2; extra == "base-frozen"
Requires-Dist: unittest-xml-reporting==3.2.0; extra == "base-frozen"
Requires-Dist: urllib3==1.26.9; extra == "base-frozen"
Requires-Dist: wheel==0.37.1; extra == "base-frozen"
Requires-Dist: wrapt==1.14.0; extra == "base-frozen"
Dynamic: author
Dynamic: author-email
Dynamic: classifier
Dynamic: description
Dynamic: description-content-type
Dynamic: home-page
Dynamic: license-file
Dynamic: provides-extra
Dynamic: requires-dist
Dynamic: summary
